LinuxInsideZhongwenban/README.md
LinuxInsideZhongwenban/__init__.py
LinuxInsideZhongwenban/__main__.py
LinuxInsideZhongwenban/file.epub
LinuxInsideZhongwenban/index.html
LinuxInsideZhongwenban/css/__init__.py
LinuxInsideZhongwenban/css/annotations.css
LinuxInsideZhongwenban/css/main.css
LinuxInsideZhongwenban/css/normalize.css
LinuxInsideZhongwenban/css/popup.css
LinuxInsideZhongwenban/font/__init__.py
LinuxInsideZhongwenban/font/fontello.eot
LinuxInsideZhongwenban/font/fontello.svg
LinuxInsideZhongwenban/font/fontello.ttf
LinuxInsideZhongwenban/font/fontello.woff
LinuxInsideZhongwenban/img/__init__.py
LinuxInsideZhongwenban/img/annotator-glyph-sprite.png
LinuxInsideZhongwenban/img/annotator-icon-sprite.png
LinuxInsideZhongwenban/img/apple-touch-icon.png
LinuxInsideZhongwenban/img/cancelfullscreen.png
LinuxInsideZhongwenban/img/close.png
LinuxInsideZhongwenban/img/fullscreen.png
LinuxInsideZhongwenban/img/loader.gif
LinuxInsideZhongwenban/img/menu-icon.png
LinuxInsideZhongwenban/img/save.png
LinuxInsideZhongwenban/img/saved.png
LinuxInsideZhongwenban/img/settings-s.png
LinuxInsideZhongwenban/img/settings.png
LinuxInsideZhongwenban/img/star.png
LinuxInsideZhongwenban/js/__init__.py
LinuxInsideZhongwenban/js/epub.js
LinuxInsideZhongwenban/js/epub.min.js
LinuxInsideZhongwenban/js/epub.min.map
LinuxInsideZhongwenban/js/hooks.min.js
LinuxInsideZhongwenban/js/hooks.min.map
LinuxInsideZhongwenban/js/reader.js
LinuxInsideZhongwenban/js/reader.js.map
LinuxInsideZhongwenban/js/reader.min.js
LinuxInsideZhongwenban/js/reader.min.map
LinuxInsideZhongwenban/js/hooks/__init__.py
LinuxInsideZhongwenban/js/hooks/extensions/__init__.py
LinuxInsideZhongwenban/js/hooks/extensions/highlight.js
LinuxInsideZhongwenban/js/libs/__init__.py
LinuxInsideZhongwenban/js/libs/jquery.min.js
LinuxInsideZhongwenban/js/libs/localforage.min.js
LinuxInsideZhongwenban/js/libs/screenfull.js
LinuxInsideZhongwenban/js/libs/screenfull.min.js
LinuxInsideZhongwenban/js/libs/zip.min.js
linux_inside_zhongwenban-2024.3.1.0.dist-info/METADATA
linux_inside_zhongwenban-2024.3.1.0.dist-info/WHEEL
linux_inside_zhongwenban-2024.3.1.0.dist-info/entry_points.txt
linux_inside_zhongwenban-2024.3.1.0.dist-info/top_level.txt
linux_inside_zhongwenban-2024.3.1.0.dist-info/RECORD
